LabRecorder.cfg
labrecorder.cp311-win_amd64.pyd
LabRecorderCLI.exe
LICENSE
lsl.dll
README.md
xdfwriter.lib
labrecorder-1.17.0.dist-info/METADATA
labrecorder-1.17.0.dist-info/WHEEL
labrecorder-1.17.0.dist-info/licenses/LICENSE
labrecorder-1.17.0.dist-info/RECORD
