Metadata-Version: 2.2
Name: labrecorder
Version: 1.17.0
Summary: Python bindings for LabRecorder recording
Author: LabStreamingLayer Developers
License: MIT
Requires-Python: >=3.8
